tweet/__init__.py
tweet/main.py
tweet/settings.py
tweet-1.3.3.dist-info/entry_points.txt
tweet-1.3.3.dist-info/WHEEL
tweet-1.3.3.dist-info/METADATA
tweet-1.3.3.dist-info/RECORD
