Metadata-Version: 2.1
Name: tweet
Version: 1.3.3
Summary: Tweet Only Library
Home-page: https://github.com/Ganariya/tweet
Author: ganariya
Author-email: ganariya2525@gmail.com
Requires-Python: >=3.9,<4.0
Classifier: Programming Language :: Python :: 3
Classifier: Programming Language :: Python :: 3.9
Requires-Dist: python-dotenv (>=0.15.0,<0.16.0)
Requires-Dist: python-twitter (>=3.5,<4.0)
Requires-Dist: rich (>=10.2.2,<11.0.0)
Requires-Dist: typer[all] (>=0.3.2,<0.4.0)
